<?xml version="1.0" encoding="utf-8"?>
	<annotation>
		<folder>E:\dataset\nfdw_datasets_0325\save_images</folder>
		<filename>g00104.jpg</filename>
		<size>
			<width>3024</width>
			<height>4032</height>
			<depth>3</depth>
		</size>
		<object>
			<name>upsuit</name>
			<pose>Unspecified</pose>
			<truncated>0</truncated>
			<difficult>0</difficult>
			<bndbox>
				<xmin>1118</xmin>
				<ymin>1304</ymin>
				<xmax>1716</xmax>
				<ymax>1977</ymax>
			</bndbox>
		</object>
		<object>
			<name>downsuit</name>
			<pose>Unspecified</pose>
			<truncated>0</truncated>
			<difficult>0</difficult>
			<bndbox>
				<xmin>914</xmin>
				<ymin>1837</ymin>
				<xmax>1408</xmax>
				<ymax>2649</ymax>
			</bndbox>
		</object>
		<object>
			<name>wrongtop</name>
			<pose>Unspecified</pose>
			<truncated>0</truncated>
			<difficult>0</difficult>
			<bndbox>
				<xmin>1376</xmin>
				<ymin>1694</ymin>
				<xmax>1671</xmax>
				<ymax>1896</ymax>
			</bndbox>
		</object>
		<object>
			<name>wrongtop</name>
			<pose>Unspecified</pose>
			<truncated>0</truncated>
			<difficult>0</difficult>
			<bndbox>
				<xmin>1082</xmin>
				<ymin>1504</ymin>
				<xmax>1275</xmax>
				<ymax>1818</ymax>
			</bndbox>
		</object>
		<object>
			<name>wrongbottom</name>
			<pose>Unspecified</pose>
			<truncated>0</truncated>
			<difficult>0</difficult>
			<bndbox>
				<xmin>853</xmin>
				<ymin>2161</ymin>
				<xmax>1088</xmax>
				<ymax>2549</ymax>
			</bndbox>
		</object>
	</annotation>
