<?xml version="1.0" encoding="utf-8"?>
	<annotation>
		<folder>E:\dataset\nfdw_datasets_0325\save_images</folder>
		<filename>g07127.jpg</filename>
		<size>
			<width>3120</width>
			<height>4160</height>
			<depth>3</depth>
		</size>
		<object>
			<name>upsuit</name>
			<pose>Unspecified</pose>
			<truncated>0</truncated>
			<difficult>0</difficult>
			<bndbox>
				<xmin>927</xmin>
				<ymin>633</ymin>
				<xmax>1859</xmax>
				<ymax>1465</ymax>
			</bndbox>
		</object>
		<object>
			<name>downsuit</name>
			<pose>Unspecified</pose>
			<truncated>0</truncated>
			<difficult>0</difficult>
			<bndbox>
				<xmin>902</xmin>
				<ymin>1528</ymin>
				<xmax>1530</xmax>
				<ymax>2411</ymax>
			</bndbox>
		</object>
		<object>
			<name>upsuit</name>
			<pose>Unspecified</pose>
			<truncated>0</truncated>
			<difficult>0</difficult>
			<bndbox>
				<xmin>2647</xmin>
				<ymin>1939</ymin>
				<xmax>3013</xmax>
				<ymax>2672</ymax>
			</bndbox>
		</object>
		<object>
			<name>downsuit</name>
			<pose>Unspecified</pose>
			<truncated>0</truncated>
			<difficult>0</difficult>
			<bndbox>
				<xmin>2697</xmin>
				<ymin>2750</ymin>
				<xmax>3041</xmax>
				<ymax>3544</ymax>
			</bndbox>
		</object>
		<object>
			<name>wrongtop</name>
			<pose>Unspecified</pose>
			<truncated>0</truncated>
			<difficult>0</difficult>
			<bndbox>
				<xmin>871</xmin>
				<ymin>572</ymin>
				<xmax>1069</xmax>
				<ymax>883</ymax>
			</bndbox>
		</object>
		<object>
			<name>wrongtop</name>
			<pose>Unspecified</pose>
			<truncated>0</truncated>
			<difficult>0</difficult>
			<bndbox>
				<xmin>1588</xmin>
				<ymin>568</ymin>
				<xmax>1810</xmax>
				<ymax>932</ymax>
			</bndbox>
		</object>
	</annotation>
