<?xml version="1.0" encoding="utf-8"?>
	<annotation>
		<folder>E:\dataset\nfdw_datasets_0325\save_images</folder>
		<filename>g15056.jpg</filename>
		<size>
			<width>3024</width>
			<height>4032</height>
			<depth>3</depth>
		</size>
		<object>
			<name>upsuit</name>
			<pose>Unspecified</pose>
			<truncated>0</truncated>
			<difficult>0</difficult>
			<bndbox>
				<xmin>1248</xmin>
				<ymin>1593</ymin>
				<xmax>1723</xmax>
				<ymax>2211</ymax>
			</bndbox>
		</object>
		<object>
			<name>downsuit</name>
			<pose>Unspecified</pose>
			<truncated>0</truncated>
			<difficult>0</difficult>
			<bndbox>
				<xmin>1270</xmin>
				<ymin>2221</ymin>
				<xmax>1708</xmax>
				<ymax>2805</ymax>
			</bndbox>
		</object>
		<object>
			<name>wrongbottom</name>
			<pose>Unspecified</pose>
			<truncated>0</truncated>
			<difficult>0</difficult>
			<bndbox>
				<xmin>1301</xmin>
				<ymin>2671</ymin>
				<xmax>1454</xmax>
				<ymax>3036</ymax>
			</bndbox>
		</object>
		<object>
			<name>wrongbottom</name>
			<pose>Unspecified</pose>
			<truncated>0</truncated>
			<difficult>0</difficult>
			<bndbox>
				<xmin>1495</xmin>
				<ymin>2683</ymin>
				<xmax>1645</xmax>
				<ymax>3021</ymax>
			</bndbox>
		</object>
	</annotation>
