<?xml version="1.0" encoding="utf-8"?>
	<annotation>
		<folder>E:\dataset\nfdw_datasets_0325\save_images</folder>
		<filename>g15299.jpg</filename>
		<size>
			<width>3024</width>
			<height>4032</height>
			<depth>3</depth>
		</size>
		<object>
			<name>upsuit</name>
			<pose>Unspecified</pose>
			<truncated>0</truncated>
			<difficult>0</difficult>
			<bndbox>
				<xmin>657</xmin>
				<ymin>1466</ymin>
				<xmax>1198</xmax>
				<ymax>2094</ymax>
			</bndbox>
		</object>
		<object>
			<name>downsuit</name>
			<pose>Unspecified</pose>
			<truncated>0</truncated>
			<difficult>0</difficult>
			<bndbox>
				<xmin>821</xmin>
				<ymin>2130</ymin>
				<xmax>1321</xmax>
				<ymax>2694</ymax>
			</bndbox>
		</object>
		<object>
			<name>wrongtop</name>
			<pose>Unspecified</pose>
			<truncated>0</truncated>
			<difficult>0</difficult>
			<bndbox>
				<xmin>686</xmin>
				<ymin>1805</ymin>
				<xmax>792</xmax>
				<ymax>2186</ymax>
			</bndbox>
		</object>
		<object>
			<name>wrongtop</name>
			<pose>Unspecified</pose>
			<truncated>0</truncated>
			<difficult>0</difficult>
			<bndbox>
				<xmin>1089</xmin>
				<ymin>1668</ymin>
				<xmax>1211</xmax>
				<ymax>2105</ymax>
			</bndbox>
		</object>
		<object>
			<name>wrongbottom</name>
			<pose>Unspecified</pose>
			<truncated>0</truncated>
			<difficult>0</difficult>
			<bndbox>
				<xmin>926</xmin>
				<ymin>2430</ymin>
				<xmax>1111</xmax>
				<ymax>2755</ymax>
			</bndbox>
		</object>
	</annotation>
