<?xml version="1.0" encoding="utf-8"?>
	<annotation>
		<folder>E:\dataset\nfdw_datasets_0325\save_images</folder>
		<filename>g24225.jpg</filename>
		<size>
			<width>3120</width>
			<height>4160</height>
			<depth>3</depth>
		</size>
		<object>
			<name>upsuit</name>
			<pose>Unspecified</pose>
			<truncated>0</truncated>
			<difficult>0</difficult>
			<bndbox>
				<xmin>300</xmin>
				<ymin>788</ymin>
				<xmax>1090</xmax>
				<ymax>1656</ymax>
			</bndbox>
		</object>
		<object>
			<name>downsuit</name>
			<pose>Unspecified</pose>
			<truncated>0</truncated>
			<difficult>0</difficult>
			<bndbox>
				<xmin>351</xmin>
				<ymin>1706</ymin>
				<xmax>995</xmax>
				<ymax>2686</ymax>
			</bndbox>
		</object>
		<object>
			<name>downsuit</name>
			<pose>Unspecified</pose>
			<truncated>0</truncated>
			<difficult>0</difficult>
			<bndbox>
				<xmin>2225</xmin>
				<ymin>2863</ymin>
				<xmax>2545</xmax>
				<ymax>3600</ymax>
			</bndbox>
		</object>
		<object>
			<name>upsuit</name>
			<pose>Unspecified</pose>
			<truncated>0</truncated>
			<difficult>0</difficult>
			<bndbox>
				<xmin>2159</xmin>
				<ymin>2132</ymin>
				<xmax>2570</xmax>
				<ymax>2814</ymax>
			</bndbox>
		</object>
		<object>
			<name>wrongtop</name>
			<pose>Unspecified</pose>
			<truncated>0</truncated>
			<difficult>0</difficult>
			<bndbox>
				<xmin>224</xmin>
				<ymin>711</ymin>
				<xmax>415</xmax>
				<ymax>1002</ymax>
			</bndbox>
		</object>
	</annotation>
