<?xml version="1.0" encoding="utf-8"?>
	<annotation>
		<folder>E:\dataset\nfdw_datasets_0325\save_images</folder>
		<filename>g26305.jpg</filename>
		<size>
			<width>1968</width>
			<height>4144</height>
			<depth>3</depth>
		</size>
		<object>
			<name>downsuit</name>
			<pose>Unspecified</pose>
			<truncated>0</truncated>
			<difficult>0</difficult>
			<bndbox>
				<xmin>686</xmin>
				<ymin>1672</ymin>
				<xmax>1014</xmax>
				<ymax>2298</ymax>
			</bndbox>
		</object>
		<object>
			<name>upsuit</name>
			<pose>Unspecified</pose>
			<truncated>0</truncated>
			<difficult>0</difficult>
			<bndbox>
				<xmin>509</xmin>
				<ymin>945</ymin>
				<xmax>1076</xmax>
				<ymax>1648</ymax>
			</bndbox>
		</object>
		<object>
			<name>wrongtop</name>
			<pose>Unspecified</pose>
			<truncated>0</truncated>
			<difficult>0</difficult>
			<bndbox>
				<xmin>963</xmin>
				<ymin>1271</ymin>
				<xmax>1091</xmax>
				<ymax>1621</ymax>
			</bndbox>
		</object>
		<object>
			<name>downcloth</name>
			<pose>Unspecified</pose>
			<truncated>0</truncated>
			<difficult>0</difficult>
			<bndbox>
				<xmin>1000</xmin>
				<ymin>1666</ymin>
				<xmax>1218</xmax>
				<ymax>2134</ymax>
			</bndbox>
		</object>
		<object>
			<name>upcloth</name>
			<pose>Unspecified</pose>
			<truncated>0</truncated>
			<difficult>0</difficult>
			<bndbox>
				<xmin>1078</xmin>
				<ymin>1188</ymin>
				<xmax>1224</xmax>
				<ymax>1669</ymax>
			</bndbox>
		</object>
	</annotation>
