<?xml version="1.0" encoding="utf-8"?>
	<annotation>
		<folder>E:\dataset\nfdw_datasets_0325\save_images</folder>
		<filename>g36599.jpg</filename>
		<size>
			<width>1968</width>
			<height>4144</height>
			<depth>3</depth>
		</size>
		<object>
			<name>downsuit</name>
			<pose>Unspecified</pose>
			<truncated>0</truncated>
			<difficult>0</difficult>
			<bndbox>
				<xmin>235</xmin>
				<ymin>3040</ymin>
				<xmax>472</xmax>
				<ymax>3417</ymax>
			</bndbox>
		</object>
		<object>
			<name>upsuit</name>
			<pose>Unspecified</pose>
			<truncated>0</truncated>
			<difficult>0</difficult>
			<bndbox>
				<xmin>197</xmin>
				<ymin>2700</ymin>
				<xmax>484</xmax>
				<ymax>3035</ymax>
			</bndbox>
		</object>
		<object>
			<name>upsuit</name>
			<pose>Unspecified</pose>
			<truncated>0</truncated>
			<difficult>0</difficult>
			<bndbox>
				<xmin>1521</xmin>
				<ymin>1322</ymin>
				<xmax>1710</xmax>
				<ymax>1617</ymax>
			</bndbox>
		</object>
		<object>
			<name>downsuit</name>
			<pose>Unspecified</pose>
			<truncated>0</truncated>
			<difficult>0</difficult>
			<bndbox>
				<xmin>1582</xmin>
				<ymin>1630</ymin>
				<xmax>1824</xmax>
				<ymax>2015</ymax>
			</bndbox>
		</object>
		<object>
			<name>wrongbottom</name>
			<pose>Unspecified</pose>
			<truncated>0</truncated>
			<difficult>0</difficult>
			<bndbox>
				<xmin>1706</xmin>
				<ymin>1838</ymin>
				<xmax>1821</xmax>
				<ymax>2038</ymax>
			</bndbox>
		</object>
	</annotation>
