<?xml version="1.0" encoding="utf-8"?>
	<annotation>
		<folder>E:\dataset\nfdw_datasets_0325\save_images</folder>
		<filename>g37193.jpg</filename>
		<size>
			<width>6000</width>
			<height>4000</height>
			<depth>3</depth>
		</size>
		<object>
			<name>upsuit</name>
			<pose>Unspecified</pose>
			<truncated>0</truncated>
			<difficult>0</difficult>
			<bndbox>
				<xmin>1718</xmin>
				<ymin>1876</ymin>
				<xmax>3000</xmax>
				<ymax>2872</ymax>
			</bndbox>
		</object>
		<object>
			<name>downsuit</name>
			<pose>Unspecified</pose>
			<truncated>0</truncated>
			<difficult>0</difficult>
			<bndbox>
				<xmin>2335</xmin>
				<ymin>2894</ymin>
				<xmax>3062</xmax>
				<ymax>3977</ymax>
			</bndbox>
		</object>
	</annotation>
