<?xml version="1.0" encoding="utf-8"?>
	<annotation>
		<folder>E:\dataset\nfdw_datasets_0325\save_images</folder>
		<filename>g39852.jpg</filename>
		<size>
			<width>4000</width>
			<height>2250</height>
			<depth>3</depth>
		</size>
		<object>
			<name>upsuit</name>
			<pose>Unspecified</pose>
			<truncated>0</truncated>
			<difficult>0</difficult>
			<bndbox>
				<xmin>2257</xmin>
				<ymin>1320</ymin>
				<xmax>2498</xmax>
				<ymax>1670</ymax>
			</bndbox>
		</object>
		<object>
			<name>downsuit</name>
			<pose>Unspecified</pose>
			<truncated>0</truncated>
			<difficult>0</difficult>
			<bndbox>
				<xmin>1705</xmin>
				<ymin>1082</ymin>
				<xmax>1944</xmax>
				<ymax>1364</ymax>
			</bndbox>
		</object>
		<object>
			<name>downsuit</name>
			<pose>Unspecified</pose>
			<truncated>0</truncated>
			<difficult>0</difficult>
			<bndbox>
				<xmin>2292</xmin>
				<ymin>1686</ymin>
				<xmax>2478</xmax>
				<ymax>2096</ymax>
			</bndbox>
		</object>
		<object>
			<name>upsuit</name>
			<pose>Unspecified</pose>
			<truncated>0</truncated>
			<difficult>0</difficult>
			<bndbox>
				<xmin>1747</xmin>
				<ymin>798</ymin>
				<xmax>1985</xmax>
				<ymax>1060</ymax>
			</bndbox>
		</object>
		<object>
			<name>upcloth</name>
			<pose>Unspecified</pose>
			<truncated>0</truncated>
			<difficult>0</difficult>
			<bndbox>
				<xmin>3157</xmin>
				<ymin>1244</ymin>
				<xmax>3278</xmax>
				<ymax>1384</ymax>
			</bndbox>
		</object>
		<object>
			<name>downcloth</name>
			<pose>Unspecified</pose>
			<truncated>0</truncated>
			<difficult>0</difficult>
			<bndbox>
				<xmin>3171</xmin>
				<ymin>1404</ymin>
				<xmax>3285</xmax>
				<ymax>1621</ymax>
			</bndbox>
		</object>
		<object>
			<name>wrongbottom</name>
			<pose>Unspecified</pose>
			<truncated>0</truncated>
			<difficult>0</difficult>
			<bndbox>
				<xmin>1720</xmin>
				<ymin>1302</ymin>
				<xmax>1841</xmax>
				<ymax>1443</ymax>
			</bndbox>
		</object>
		<object>
			<name>wrongtop</name>
			<pose>Unspecified</pose>
			<truncated>0</truncated>
			<difficult>0</difficult>
			<bndbox>
				<xmin>1738</xmin>
				<ymin>816</ymin>
				<xmax>1807</xmax>
				<ymax>903</ymax>
			</bndbox>
		</object>
	</annotation>
